ntt/.DS_Store
ntt/__init__.py
ntt/draw/__init__.py
ntt/draw/polygone.py
ntt/draw/primitives.py
ntt/frames/.DS_Store
ntt/frames/__init__.py
ntt/frames/crop_image.py
ntt/frames/frame_extraction.py
ntt/frames/frame_generation.py
ntt/frames/frame_overlay.py
ntt/frames/n_frame_extraction.py
ntt/frames/processing.py
ntt/sounds/.DS_Store
ntt/sounds/__init__.py
ntt/sounds/sound_detection.py
ntt/sounds/sound_gap_measure.py
ntt/sounds/sound_generation.py
ntt/utils/__init__.py
ntt/utils/debug.py
ntt/utils/dicts.py
ntt/utils/files.py
ntt/utils/index.py
ntt/utils/json_to_text.py
ntt/utils/random.py
ntt/utils/strings.py
ntt/utils/temporal.py
ntt/utils/text_to_json.py
ntt/videos/.DS_Store
ntt/videos/__init__.py
ntt/videos/compress.py
ntt/videos/create_clip.py
ntt/videos/dimensions.py
ntt/videos/duration.py
ntt/videos/get_fourcc.py
ntt/videos/peak.py
ntt/videos/shake_video.py
ntt/videos/show.py
ntt/videos/split_video.py
ntt/videos/stich.py
ntt/videos/video_generation.py
ntt/videos/video_overlay.py
ntt/videos/zoom.py
ntt-0.1.3.dist-info/WHEEL
ntt-0.1.3.dist-info/METADATA
ntt-0.1.3.dist-info/RECORD
