Metadata-Version: 2.4
Name: ntt
Version: 0.1.3
Summary: Library for sport analysis
Author-email: Romain Vuillemot <romain.vuillemot@gmail.com>
Maintainer-email: Romain Vuillemot <romain.vuillemot@gmail.com>
Requires-Python: >=3.7
Classifier: Development Status :: 2 - Pre-Alpha
Classifier: Intended Audience :: Developers
Classifier: Operating System :: OS Independent
Classifier: Natural Language :: English
Classifier: Programming Language :: Python :: 3 :: Only
Classifier: Topic :: Multimedia :: Video
Classifier: Topic :: Multimedia :: Sound/Audio :: Analysis
Classifier: Topic :: Scientific/Engineering :: Image Processing
Classifier: Topic :: Scientific/Engineering :: Visualization
Classifier: Topic :: Software Development :: Libraries
Requires-Dist: requests
Requires-Dist: opencv-python
Requires-Dist: ffmpeg-python
Requires-Dist: moviepy
Requires-Dist: scipy
Requires-Dist: python-dotenv
Requires-Dist: matplotlib
Requires-Dist: pyAudioAnalysis
Requires-Dist: eyed3
Requires-Dist: pydub
Requires-Dist: librosa
Requires-Dist: black ; extra == "dev"
Requires-Dist: pytest ; extra == "dev"
Requires-Dist: flit ; extra == "dev"
Requires-Dist: sphinx ; extra == "dev"
Requires-Dist: sphinx-rtd-theme ; extra == "dev"
Requires-Dist: pydata-sphinx-theme ; extra == "dev"
Requires-Dist: sphinx-design ; extra == "dev"
Requires-Dist: nbsphinx ; extra == "dev"
Requires-Dist: nbsphinx-link ; extra == "dev"
Requires-Dist: ipywidgets ; extra == "dev"
Requires-Dist: sphinxcontrib-mermaid ; extra == "dev"
Requires-Dist: sphinx-copybutton ; extra == "dev"
Project-URL: CI, https://app.circleci.com/pipelines/github/centralelyon/ntt
Project-URL: Documentation, https://ntt.readthedocs.io/
Project-URL: GitHub, https://github.com/centralelyon/ntt/
Project-URL: Issues, https://github.com/centralelyon/ntt/issues
Provides-Extra: dev
